[
    {
        "fullstartdate": "202410101500",
        "date": "20241011",
        "url": "https://www.bing.com/th?id=OHR.CelticColours_JA-JP6953032126_1920x1080.jpg",
        "urlbase": "https://www.bing.com/th?id=OHR.CelticColours_JA-JP6953032126",
        "copyright": "ケープ・ブレトン島, カナダ ノバスコシア州 (© Cavan Images/Alamy)",
        "copyrightKeyword": "ケープ・ブレトン島",
        "hsh": "1ec17bff5d8b3769c0d580b5c726411f",
        "description": "ここはカナダ・ノバスコシア州のケープ・ブレトン島。島の中央部にはブラドー湖が広がり、海岸線や山々、森を通り抜ける風光明媚なドライブコースで知られています。また、19 世紀に流入したスコットランドやアイルランド系移民が多く、ケルト文化が色濃く残っています…"
    },
    {
        "fullstartdate": "202410091500",
        "date": "20241010",
        "url": "https://www.bing.com/th?id=OHR.SoranoItaly_JA-JP6459075522_1920x1080.jpg",
        "urlbase": "https://www.bing.com/th?id=OHR.SoranoItaly_JA-JP6459075522",
        "copyright": "ソラーノ, イタリア トスカーナ州 (© Luigi Vaccarella/eStock Photo)",
        "copyrightKeyword": "ソラーノ イタリア",
        "hsh": "14313d0054d4c78a83d605d6c7e24d67",
        "description": "ここはソラーノ。イタリア・トスカーナ州グロッセート県の断崖絶壁の上にある美しい町です。石造りの建物が立ち並び、中世の雰囲気を今なお残しています。古い石畳の道を歩いて町の一番高い場所まで登ると、11 世紀に建てられたオルシーニ要塞が見られます…"
    },
    {
        "fullstartdate": "202410081500",
        "date": "20241009",
        "url": "https://www.bing.com/th?id=OHR.AspensColorado_JA-JP6244858068_1920x1080.jpg",
        "urlbase": "https://www.bing.com/th?id=OHR.AspensColorado_JA-JP6244858068",
        "copyright": "マーブル近郊に自生するアスペン, 米国 コロラド州 (© Jason Hatfield/Tandem Stills + Motion)",
        "copyrightKeyword": "北米のアスペンの木",
        "hsh": "7a81ada97e471fdb4c880131251a8c6f",
        "description": "今日の画像は米国・コロラド州のマーブル近郊に自生するアスペンの森です。アスペンは北米の涼しい地域に広く分布する落葉樹で、美しい銀白色の樹皮と、秋になると黄金色に染まる葉が特徴です…"
    },
    {
        "fullstartdate": "202410071500",
        "date": "20241008",
        "url": "https://www.bing.com/th?id=OHR.Kanro2024_JA-JP5787966494_1920x1080.jpg",
        "urlbase": "https://www.bing.com/th?id=OHR.Kanro2024_JA-JP5787966494",
        "copyright": "秋の八甲田ロープウェイ,  青森県 青森市 (© Torsakarin/Getty Images)",
        "copyrightKeyword": "秋の八甲田ロープウェイ",
        "hsh": "4823b960206f53db2bb2c2004bc2321d",
        "description": "今日 10 月 8 日は二十四節気の｢寒露｣で、露が冷気によって凍り、朝晩の気温がぐっと下がるころです。秋が深まり、紅葉が美しく色づく時期でもあります。ここ、青森県青森市にある八甲田山の紅葉も、見頃の時期を迎えます…"
    },
    {
        "fullstartdate": "202410061500",
        "date": "20241007",
        "url": "https://www.bing.com/th?id=OHR.ElbePhilharmonic_JA-JP5541486306_1920x1080.jpg",
        "urlbase": "https://www.bing.com/th?id=OHR.ElbePhilharmonic_JA-JP5541486306",
        "copyright": "エルプフィルハーモニー・ハンブルク, ドイツ (© Canetti/Shutterstock)",
        "copyrightKeyword": "エルプフィルハーモニー・ハンブルク",
        "hsh": "96232a6531940f2cac6a5cdc749c6ff0",
        "description": "金閣寺や姫路城などの歴史的な建築物から、「金沢 21 世紀美術館」や「東京スカイツリー」などの現代建築技術の結晶まで、日本には多くの名建築物があります。そして、今日 10 月 7 日はこれらの建築物を称える「世界建築の日」です。1985 年に国際建築家連合によって創設され、毎年 10 月の第 1 月曜日に祝われます…"
    },
    {
        "fullstartdate": "202410051500",
        "date": "20241006",
        "url": "https://www.bing.com/th?id=OHR.KochiaJapan_JA-JP5196113182_1920x1080.jpg",
        "urlbase": "https://www.bing.com/th?id=OHR.KochiaJapan_JA-JP5196113182",
        "copyright": "国営ひたち海浜公園, 茨城県 ひたちなか市 (© DigiPub/Getty Images)",
        "copyrightKeyword": "国営ひたち海浜公園",
        "hsh": "35e833c321e73d17f47794cb778cda72",
        "description": "国営ひたち海浜公園の「みはらしの丘」は、春は青いネモフィラで彩られ、秋にはコキアで真っ赤に色づきます。そして、 9 月 27 日から今日 10 月 6 日まで行われているのが「コキアライトアップ」です。約 4 万本のコキアが音楽に合わせてカラフルな光で照らされる他、ダンスのステージショーや飲食イベントなどが楽しめます…"
    },
    {
        "fullstartdate": "202410041500",
        "date": "20241005",
        "url": "https://www.bing.com/th?id=OHR.ElephantTeacher_JA-JP4940024317_1920x1080.jpg",
        "urlbase": "https://www.bing.com/th?id=OHR.ElephantTeacher_JA-JP4940024317",
        "copyright": "ツァボイースト国立公園のアフリカゾウ, ケニア (© Neil Bowman/Minden Pictures)",
        "copyrightKeyword": "ツァボイースト国立公園のアフリカゾウ",
        "hsh": "50f87ac53ef298bdf4d0998141267f3e",
        "description": "今日 10 月 5 日は世界教師デー。教師に感謝し、教育における彼らの貢献を称える日として、1994 年から開催されており、現在、100 以上の国々で祝われています。日本ではまだあまり浸透していませんが、この取り組みを広めるために、記念フォーラムや感謝セレモニーなど、教師への感謝を示すイベントや啓発・広報活動が行われています…"
    },
    {
        "fullstartdate": "202410031500",
        "date": "20241004",
        "url": "https://www.bing.com/th?id=OHR.EuropaMoon_JA-JP4639297209_1920x1080.jpg",
        "urlbase": "https://www.bing.com/th?id=OHR.EuropaMoon_JA-JP4639297209",
        "copyright": "木星の衛星エウロパ (© NASA/JPL-Caltech/SETI Institute)",
        "copyrightKeyword": "木星の衛星エウロパ",
        "hsh": "af37367af127a2f1a60e05372c7df6bf"
    }
]