[
    {
        "fullstartdate": "202412191500",
        "date": "20241220",
        "url": "https://www.bing.com/th?id=OHR.SantaClausVillage_JA-JP9442890850_1920x1080.jpg",
        "urlbase": "https://www.bing.com/th?id=OHR.SantaClausVillage_JA-JP9442890850",
        "copyright": "ロヴァニエミ近郊のサンタクロース村, フィンランド (© Smelov/Shutterstock)",
        "copyrightKeyword": "ロヴァニエミ近郊のサンタクロース村",
        "hsh": "f613dcece55b74e7f322f2d5619f64ca",
        "description": "ロヴァニエミは、フィンランド北部、ラップランド地方の中心都市です。北極圏のすぐ近くに位置しており、雪に覆われた魅惑的な森や神秘的なオーロラなど、北極圏の冬の魅力を満喫できる場所です。また、サンタクロースの故郷として世界中で知られています…"
    },
    {
        "fullstartdate": "202412181500",
        "date": "20241219",
        "url": "https://www.bing.com/th?id=OHR.SibiuRomania_JA-JP9171991249_1920x1080.jpg",
        "urlbase": "https://www.bing.com/th?id=OHR.SibiuRomania_JA-JP9171991249",
        "copyright": "歴史的な都市シビウ, ルーマニア (© Calin Stan/Alamy)",
        "copyrightKeyword": "ルーマニアのシビウ",
        "hsh": "86f6da7394d9d47d70c864271978a037",
        "description": "冬の寒さが深まる中、ルーマニアで最も人気のあるクリスマスマーケットが、シビウの大広場で開催されます。美しいイルミネーションで飾られた広場では、ルーマニアの伝統的な甘いパン「コゾナック」や、香り豊かなホットワインなどを楽しむことができます…"
    },
    {
        "fullstartdate": "202412171500",
        "date": "20241218",
        "url": "https://www.bing.com/th?id=OHR.NutcrackerBallet_JA-JP8484350110_1920x1080.jpg",
        "urlbase": "https://www.bing.com/th?id=OHR.NutcrackerBallet_JA-JP8484350110",
        "copyright": "くるみ割り人形 (© Caroline Holden/Alamy)",
        "copyrightKeyword": "バレエ くるみ割り人形",
        "hsh": "1a434f73d962cea01ba6a4ed86029780",
        "description": "冬の風物詩、クリスマスシーズン恒例のバレエ公演といえば「くるみ割り人形」です。1892 年に初演されたこのバレエ作品は、ニューヨーク・シティ・バレエ団や、写真のイングリッシュ・ナショナル・バレエ団、そして日本の新国立劇場バレエ団など、多くの有名なバレエ団によって上演されています…"
    },
    {
        "fullstartdate": "202412161500",
        "date": "20241217",
        "url": "https://www.bing.com/th?id=OHR.ReinefjordenNorway_JA-JP8145740016_1920x1080.jpg",
        "urlbase": "https://www.bing.com/th?id=OHR.ReinefjordenNorway_JA-JP8145740016",
        "copyright": "美しい村レーヌ, ノルウェー (© Pilat666/Getty Images)",
        "copyrightKeyword": "ノルウェーのレーヌ",
        "hsh": "19f13067b64fc1ef051322b2259b93ee",
        "description": "ここはレーヌ。ノルウェーのロフォーテン諸島に位置する、人口約 300 人ほどの小さな漁村です。古くから漁業が盛んな地域であり、現在でも魚の加工・販売が行われています。また、観光地としても人気があり、ノルウェー最大の雑誌「Allers」によって「ノルウェーで最も美しい村」にも選ばれました…"
    },
    {
        "fullstartdate": "202412151500",
        "date": "20241216",
        "url": "https://www.bing.com/th?id=OHR.SalzburgSnow_JA-JP7845943575_1920x1080.jpg",
        "urlbase": "https://www.bing.com/th?id=OHR.SalzburgSnow_JA-JP7845943575",
        "copyright": "ザルツブルク, オーストリア (© bluejayphoto/Getty Images)",
        "copyrightKeyword": "ザルツブルク",
        "hsh": "8c8a45ccd85ab3451921b1e9fcad0e6f",
        "description": "ここはオーストリアの美しい都市、ザルツブルクです。中世の建築物やバロック様式の教会が立ち並ぶその旧市街は、ユネスコの世界遺産にも登録されています。特に、丘の上にそびえ立つ白亜のホーエンザルツブルク城は、その壮大な景観で訪れる人々を魅了します…"
    },
    {
        "fullstartdate": "202412141500",
        "date": "20241215",
        "url": "https://www.bing.com/th?id=OHR.MisurinaLake_JA-JP7561735635_1920x1080.jpg",
        "urlbase": "https://www.bing.com/th?id=OHR.MisurinaLake_JA-JP7561735635",
        "copyright": "ミズリーナ湖, イタリア (© Marco Bottigelli/Getty Images)",
        "copyrightKeyword": "ミズリーナ湖",
        "hsh": "cbe5ca7f1d6fc325c431862133d2cc38",
        "description": "ここはイタリアのドロミテ山脈に位置するミズリーナ湖。海抜 1754m に位置し、周囲は 2.6km に及びます。湖畔に建つホテルや、壮大な山々が湖面に鏡のように映る美しい景観が魅力的です。また、この湖は、巨人の王が娘の死を嘆き、流した涙によってできたという伝説も残っています…"
    },
    {
        "fullstartdate": "202412131500",
        "date": "20241214",
        "url": "https://www.bing.com/th?id=OHR.NorthernHawkOwl_JA-JP7268842450_1920x1080.jpg",
        "urlbase": "https://www.bing.com/th?id=OHR.NorthernHawkOwl_JA-JP7268842450",
        "copyright": "オナガフクロウ, カナダ (© pchoui/Getty Images)",
        "copyrightKeyword": "オナガフクロウ",
        "hsh": "0e5da5ecb4195c35d8ac707767b4cb33",
        "description": "今日 12 月 14 日から 1 月 5 日までの間、米国全土で数万人の愛鳥家ボランティアが「クリスマス・バード・カウント」という野鳥の個体数を数えるイベントに参加します。個々のカウントは、約 24km 幅の円内で行われ、合計 2500 以上の場所からデータが収集されます…"
    },
    {
        "fullstartdate": "202412121500",
        "date": "20241213",
        "url": "https://www.bing.com/th?id=OHR.ChristmasBudapest_JA-JP6583292404_1920x1080.jpg",
        "urlbase": "https://www.bing.com/th?id=OHR.ChristmasBudapest_JA-JP6583292404",
        "copyright": "聖イシュトヴァーン大聖堂, ハンガリー (© Calin Stan/Shutterstock)",
        "copyrightKeyword": "聖イシュトヴァーン大聖堂",
        "hsh": "3aaca313725d225db09e14d851e88d5f"
    }
]