[
    {
        "fullstartdate": "202509251600",
        "date": "20250926",
        "url": "https://www.bing.com/th?id=OHR.AutumnChipmunk_ZH-CN6224482683_1920x1080.jpg",
        "urlbase": "https://www.bing.com/th?id=OHR.AutumnChipmunk_ZH-CN6224482683",
        "copyright": "最小花栗鼠, 库特奈国家公园, 蒙大拿州, 美国 (© Donald M. Jones/Minden Pictures)",
        "copyrightKeyword": "最小花栗鼠",
        "hsh": "2885513666b93587b3f34108402e97fc"
    },
    {
        "fullstartdate": "202509241600",
        "date": "20250925",
        "url": "https://www.bing.com/th?id=OHR.FortChittorgarh_ZH-CN5999553283_1920x1080.jpg",
        "urlbase": "https://www.bing.com/th?id=OHR.FortChittorgarh_ZH-CN5999553283",
        "copyright": "奇陶尔加尔堡, 拉贾斯坦邦, 印度 (© chetansoni/Shutterstock)",
        "copyrightKeyword": "奇陶尔加尔堡印度",
        "hsh": "1ce53069edceeee5aa5081dc3746a2cc"
    },
    {
        "fullstartdate": "202509231600",
        "date": "20250924",
        "url": "https://www.bing.com/th?id=OHR.BearLodge_ZH-CN5880511888_1920x1080.jpg",
        "urlbase": "https://www.bing.com/th?id=OHR.BearLodge_ZH-CN5880511888",
        "copyright": "魔鬼塔国家纪念碑, 怀俄明州，美国 (© Laura Hedien/Getty Images)",
        "copyrightKeyword": "魔鬼塔国家纪念碑",
        "hsh": "35c7faae9c07a66ae09233ebd111c471"
    },
    {
        "fullstartdate": "202509221600",
        "date": "20250923",
        "url": "https://www.bing.com/th?id=OHR.AutumnalEquinoxY25_ZH-CN5692548297_1920x1080.jpg",
        "urlbase": "https://www.bing.com/th?id=OHR.AutumnalEquinoxY25_ZH-CN5692548297",
        "copyright": "航拍中国江苏省常州翠竹公园 (© Xu Changyu/Getty images)",
        "copyrightKeyword": "秋分",
        "hsh": "414618577ac45d408003fa84bf89c1c4"
    },
    {
        "fullstartdate": "202509211600",
        "date": "20250922",
        "url": "https://www.bing.com/th?id=OHR.AspenEquinox_ZH-CN5474695693_1920x1080.jpg",
        "urlbase": "https://www.bing.com/th?id=OHR.AspenEquinox_ZH-CN5474695693",
        "copyright": "秋日的白杨树，鱼湖国家森林，犹他州，美国 (© Danita Delimont/Getty Images)",
        "copyrightKeyword": "白杨树",
        "hsh": "ebb7caec18e054740bfebc0a6e7cdc66"
    },
    {
        "fullstartdate": "202509201600",
        "date": "20250921",
        "url": "https://www.bing.com/th?id=OHR.IceOtters_ZH-CN5393791969_1920x1080.jpg",
        "urlbase": "https://www.bing.com/th?id=OHR.IceOtters_ZH-CN5393791969",
        "copyright": "海獭，威廉王子湾，阿拉斯加州，美国 (© Gerald Corsi/Getty Images)",
        "copyrightKeyword": "海獭",
        "hsh": "8971e4414904f14f2d090d1b59c2f114"
    },
    {
        "fullstartdate": "202509191600",
        "date": "20250920",
        "url": "https://www.bing.com/th?id=OHR.OktoberfestSwing_ZH-CN5270146600_1920x1080.jpg",
        "urlbase": "https://www.bing.com/th?id=OHR.OktoberfestSwing_ZH-CN5270146600",
        "copyright": "慕尼黑啤酒节上的旋转木马，慕尼黑，巴伐利亚，德国 (© LOOK-foto/Alamy)",
        "copyrightKeyword": "慕尼黑啤酒节",
        "hsh": "733bd460c646ad947d6bfffaa51f52ac"
    },
    {
        "fullstartdate": "202509181600",
        "date": "20250919",
        "url": "https://www.bing.com/th?id=OHR.ThousandIslands_ZH-CN3197750437_1920x1080.jpg",
        "urlbase": "https://www.bing.com/th?id=OHR.ThousandIslands_ZH-CN3197750437",
        "copyright": "千岛群岛地区，圣劳伦斯河，美加边境 (© benedek/Getty Images)",
        "copyrightKeyword": "千岛群岛 北美洲",
        "hsh": "d89d3125a623a1ccf7f84bfce50f1a82"
    }
]