[
    {
        "fullstartdate": "202508170400",
        "date": "20250818",
        "url": "https://www.bing.com/th?id=OHR.LyngvigLighthouse_FR-CA6450462994_1920x1080.jpg",
        "urlbase": "https://www.bing.com/th?id=OHR.LyngvigLighthouse_FR-CA6450462994",
        "copyright": "Phare de Lyngvig, Hvide Sande, Danemark (© Caroline Brundle Bugge/Getty Images)",
        "copyrightKeyword": "phare",
        "hsh": "09ab5282deddd1bad3e00bc498f99b98"
    },
    {
        "fullstartdate": "202508160400",
        "date": "20250817",
        "url": "https://www.bing.com/th?id=OHR.ColorfulBeehives_FR-CA6306812917_1920x1080.jpg",
        "urlbase": "https://www.bing.com/th?id=OHR.ColorfulBeehives_FR-CA6306812917",
        "copyright": "Ruches colorées, Italie (© Roberto Caucino/Shutterstock)",
        "copyrightKeyword": "ruche et abeille",
        "hsh": "9361097bae8d7dc656c3b1f6c1ac0add"
    },
    {
        "fullstartdate": "202508150400",
        "date": "20250816",
        "url": "https://www.bing.com/th?id=OHR.CNExhibit_FR-CA1821188983_1920x1080.jpg",
        "urlbase": "https://www.bing.com/th?id=OHR.CNExhibit_FR-CA1821188983",
        "copyright": "L’attraction Orbitor à l’Exposition nationale canadienne, Toronto (© James Hackland/Alamy Stock Photo)",
        "copyrightKeyword": "Exposition nationale canadienne",
        "hsh": "546674443e32582ff623d99f18af9f0a"
    },
    {
        "fullstartdate": "202508140400",
        "date": "20250815",
        "url": "https://www.bing.com/th?id=OHR.PizNairPeak_FR-CA6049160624_1920x1080.jpg",
        "urlbase": "https://www.bing.com/th?id=OHR.PizNairPeak_FR-CA6049160624",
        "copyright": "Station téléphérique du mont Piz Nair, Grisons, Suisse (© Roberto Moiola/Alamy)",
        "copyrightKeyword": "mont Piz Nair",
        "hsh": "2c72292ecd9e02f32d01d9fe8959d8a0"
    },
    {
        "fullstartdate": "202508130400",
        "date": "20250814",
        "url": "https://www.bing.com/th?id=OHR.CoronaArch_FR-CA5923808590_1920x1080.jpg",
        "urlbase": "https://www.bing.com/th?id=OHR.CoronaArch_FR-CA5923808590",
        "copyright": "Descente en rappel de Corona Arch, Utah, États-Unis (© Grant Ordelheide/TANDEM Stills + Motion)",
        "copyrightKeyword": "arche naturelle",
        "hsh": "af8050d2e047aa5e5bc3c77a9e7b0889"
    },
    {
        "fullstartdate": "202508120400",
        "date": "20250813",
        "url": "https://www.bing.com/th?id=OHR.KenyaElephants_FR-CA5786228560_1920x1080.jpg",
        "urlbase": "https://www.bing.com/th?id=OHR.KenyaElephants_FR-CA5786228560",
        "copyright": "Troupeau d’éléphants d’Afrique, parc national d’Amboseli, Kenya (© Chase Dekker/Minden Pictures)",
        "copyrightKeyword": "journée mondiale de l'éléphant",
        "hsh": "b9ffe89dd91166b2a33856edf381e683"
    },
    {
        "fullstartdate": "202508110400",
        "date": "20250812",
        "url": "https://www.bing.com/th?id=OHR.SantaMaddalena_FR-CA5380736106_1920x1080.jpg",
        "urlbase": "https://www.bing.com/th?id=OHR.SantaMaddalena_FR-CA5380736106",
        "copyright": "Village de Santa Maddalena, Dolomites, Italie (© Sakrapee Nopparat/Getty Images)",
        "copyrightKeyword": "Dolomites Italie",
        "hsh": "55b8ffd428505b4d99dbc568fc55456d"
    },
    {
        "fullstartdate": "202508100400",
        "date": "20250811",
        "url": "https://www.bing.com/th?id=OHR.LionessKenya_FR-CA5236345175_1920x1080.jpg",
        "urlbase": "https://www.bing.com/th?id=OHR.LionessKenya_FR-CA5236345175",
        "copyright": "Lionne dans la réserve nationale du Masai Mara, Kenya (© Tandem Stock/Adobe Stock)",
        "copyrightKeyword": "Journée mondiale du lion",
        "hsh": "df095fcfd3d68c68675ca57260969a2b"
    }
]